CHANGES.txt
LICENSE.txt
MANIFEST.in
README.md
README.rst
setup.py
Pareidoscope.egg-info/PKG-INFO
Pareidoscope.egg-info/SOURCES.txt
Pareidoscope.egg-info/dependency_links.txt
Pareidoscope.egg-info/requires.txt
Pareidoscope.egg-info/top_level.txt
bin/pareidoscope_associated_structures
bin/pareidoscope_association_strength
bin/pareidoscope_collexeme_analysis
bin/pareidoscope_corpus_to_sqlite
bin/pareidoscope_covarying_collexemes
bin/pareidoscope_draw_graphs
doc/ex_associated_structures.json
doc/ex_association_two_structures.json
doc/ex_collexeme_analysis.json
doc/ex_covarying_collexemes.json
doc/monotransitive_give_01.png
doc/monotransitive_give_02.png
doc/monotransitive_give_03.png
doc/monotransitive_give_04.png
doc/piotr_lexicalized_queries.json
doc/piotr_unlexicalized_queries.json
pareidoscope/__init__.py
pareidoscope/frequency.py
pareidoscope/query.py
pareidoscope/star_extraction.py
pareidoscope/subgraph_enumeration.py
pareidoscope/subgraph_isomorphism.py
pareidoscope/utils/__init__.py
pareidoscope/utils/collexeme_database.py
pareidoscope/utils/conllu.py
pareidoscope/utils/cwb.py
pareidoscope/utils/database.py
pareidoscope/utils/helper.py
pareidoscope/utils/nx_graph.py
pareidoscope/utils/parallelization.py
pareidoscope/utils/random_trees.py
pareidoscope/utils/statistics.py